universalPip/__init__.py
universalPip/cli.py
universalPip/universalPip.py
universalpip-0.1.1.dist-info/METADATA
universalpip-0.1.1.dist-info/WHEEL
universalpip-0.1.1.dist-info/entry_points.txt
universalpip-0.1.1.dist-info/licenses/LICENSE
universalpip-0.1.1.dist-info/RECORD
