Metadata-Version: 2.3
Name: universalPip
Version: 0.1.1
Summary: Creates an Universal2 distribution for given package on PyPI and installs it.
Project-URL: Homepage, https://github.com/MaximeLeMagicien/uPip
Project-URL: Issues, https://github.com/MaximeLeMagicien/uPip/issues
Project-URL: Changelog, https://github.com/MaximeLeMagicien/uPip/blob/main/Changelog.md
Author-email: Maxime CORDELLA <maxime.cordella.1@ulaval.ca>
License-Expression: MIT
License-File: LICENSE
Keywords: Universal2,arm64,macOSX,pyinstaller,x86_64
Classifier: Development Status :: 4 - Beta
Classifier: Environment :: Console
Classifier: Intended Audience :: Developers
Classifier: License :: OSI Approved :: MIT License
Classifier: Operating System :: MacOS
Classifier: Programming Language :: Python :: 3
Requires-Python: >=3.8
Requires-Dist: asyncio
Requires-Dist: delocate
Requires-Dist: regex
Requires-Dist: requests
